py_adaptive-0.1.5.dist-info/licenses/LICENSE
pyadaptive/__init__.py
pyadaptive/adaptive_auth.py
pyadaptive/adaptive_batch.py
pyadaptive/adaptive_import.py
pyadaptive/adaptive_oapif.py
pyadaptive/adaptive_types.py
pyadaptive/py.typed
py_adaptive-0.1.5.dist-info/METADATA
py_adaptive-0.1.5.dist-info/WHEEL
py_adaptive-0.1.5.dist-info/top_level.txt
py_adaptive-0.1.5.dist-info/RECORD
