Metadata-Version: 2.4
Name: py-adaptive
Version: 0.1.5
Summary: Python library used for simplifying data interaction with Adaptive API.
Author-email: Mikal Røli <mikal.roli@avinet.no>, Jørgen Reimer Nystad <jorgen.nystad@avinet.no>
License:                     GNU GENERAL PUBLIC LICENSE
Classifier: Programming Language :: Python :: 3
Classifier: License :: OSI Approved :: GNU General Public License v3 or later (GPLv3+)
Classifier: Operating System :: OS Independent
Requires-Python: >=3.10
License-File: LICENSE
Requires-Dist: python-dotenv>=0.21.0
Requires-Dist: requests>=2.31.0
Requires-Dist: python-keycloak>=3.1.0
Dynamic: license-file
